src/__init__.py
src/decorators.py
src/main.py
src/models/__init__.py
src/models/rolling.py
src/models/strategy/__init__.py
src/models/strategy/blue_green/__init__.py
src/models/strategy/blue_green/step.py
src/models/strategy/blue_green/steps/__init__.py
src/models/strategy/blue_green/steps/check_active_step.py
src/models/strategy/blue_green/steps/check_autoscaling_size_step.py
src/models/strategy/blue_green/steps/rereoute_traffic_step.py
src/models/strategy/blue_green/steps/set_new_autoscaling_group_size.py
src/models/strategy/blue_green/steps/set_old_autoscaling_group_size.py
src/models/strategy/blue_green/steps/terminate_inactive_instances_step.py
src/models/strategy/blue_green/steps/wait_until_new_instances_are_booted.py
src/models/strategy/blue_green/steps/wait_until_new_instances_are_healthy.py
src/models/strategy/blue_green/steps/wait_until_new_instances_are_targeted.py
src/models/strategy/blue_green/strategy.py
src/models/strategy/stategy.py
src/utils/__init__.py
src/utils/aws_autoscaling_group.py
src/utils/aws_instance.py
src/utils/aws_load_balancer.py
src/utils/aws_target_group.py
rolling_replacer-1.2.0.dist-info/entry_points.txt
rolling_replacer-1.2.0.dist-info/WHEEL
rolling_replacer-1.2.0.dist-info/METADATA
rolling_replacer-1.2.0.dist-info/RECORD
